{
"Magikarp":"1165",
"Bayleef":"5207",
"Quilava":"4375",
"Croconaw":"5085",
"Ivysaur":"5238",
"Charmeleon":"5085",
"Wartortle":"4503",
"Metapod":"1534",
"Wailmer":"3369",
"Swablu":"2766",
"Snorunt":"2825",
"Muk":"11200",
"Weezing":"11245",
"Exeggutor":"12633",
"Electabuzz":"11311",
"Magmar":"11610",
"Magneton":"14172",
"Sableye":"8266",
"Sandslash":"12312",
"Tentacruel":"12190",
"Marowak":"9891",
"Cloyster":"15678",
"Mawile":"9403",
"Dewgong":"9216",
"Slowbro":"11776",
"Alakazam":"22646",
"Machamp":"18144",
"Gengar":"19768",
"Vaporeon":"16696",
"Jolteon":"19883",
"Flareon":"21155",
"Ninetales":"14914",
"Scyther":"17358",
"Omastar":"18915",
"Porygon":"11419",
"Azumarill":"8989",
"Piloswine":"13663",
"Jynx":"18296",
"Aerodactyl":"17924",
"Starmie":"17384",
"Claydol":"13450",
"Venusaur":"26921",
"Charizard":"28485",
"Blastoise":"24162",
"Rhydon":"30512",
"Snorlax":"25419",
"Lapras":"21768",
"Tyranitar":"34707",
"Poliwrath":"24247",
"Victrebell":"23780",
"Golem":"30572",
"Nidoking":"24873",
"Nidoqueen":"23216",
"Absol":"26262",
"Aggron":"33458",
"Feraligator":"27740",
"Articuno":"37603",
"Zapdos":"42961",
"Moltres":"41953",
"Raikou":"42932",
"Entei":"38628",
"Suicune":"34471",
"Lugia":"42753",
"Ho-Oh":"48276",
"Groudon":"51968",
"Kyogre":"51968",
"Rayquaza":"45468",
"Mewtwo":"49430",
"Latios" : "49322"
}
